src/__init__.py
src/config.py
src/info.py
src/project_management.py
temis.py
temis-0.1.7.dist-info/entry_points.txt
temis-0.1.7.dist-info/METADATA
temis-0.1.7.dist-info/WHEEL
temis-0.1.7.dist-info/RECORD
