Metadata-Version: 2.1
Name: temis
Version: 0.1.7
Summary: A python project manager for using virtual envs and a requirements.txt file. This project is just a practice project, as poetry (used for creating this project) has the same purpose and a bigger community behind it. It is not recommended to use this project in any production environment.
License: MIT licensing
Author: Mario
Author-email: mariohertu@gmail.com
Requires-Python: >=3.12,<4.0
Classifier: License :: Other/Proprietary License
Classifier: Programming Language :: Python :: 3
Classifier: Programming Language :: Python :: 3.12
Requires-Dist: click (>=8.1.7,<9.0.0)
